face.py
opencv_samjones-0.0.1.dist-info/License.txt
opencv_samjones-0.0.1.dist-info/METADATA
opencv_samjones-0.0.1.dist-info/WHEEL
opencv_samjones-0.0.1.dist-info/top_level.txt
opencv_samjones-0.0.1.dist-info/RECORD
